hallo_ut/__init__.py
hallo_ut/__main__.py
hallo_ut/constants.py
hallo_ut/faq.py
hallo_ut/hallo_ut.py
hallo_ut/tiket/__init__.py
hallo_ut/tiket/priority_tiket.py
hallo_ut/tiket/tiket.py
hallo_ut/tiket/topik_tiket.py
hallo_ut/utils.py
hallo_ut-0.5.3.dist-info/entry_points.txt
hallo_ut-0.5.3.dist-info/LICENSE
hallo_ut-0.5.3.dist-info/WHEEL
hallo_ut-0.5.3.dist-info/METADATA
hallo_ut-0.5.3.dist-info/RECORD
