Metadata-Version: 2.1
Name: hallo-ut
Version: 0.5.3
Summary: SDK Python Layanan Informasi & Bantuan Universitas Terbuka
Keywords: univterbuka,hallo-ut,faq
Author: hexatester
Author-email: habibrohman@protonmail.com
Requires-Python: >=3.8,<4.0
Classifier: Development Status :: 4 - Beta
Classifier: Intended Audience :: Developers
Classifier: License :: OSI Approved :: GNU General Public License v3 (GPLv3)
Classifier: Operating System :: OS Independent
Classifier: Programming Language :: Python :: 3
Classifier: Programming Language :: Python :: 3.8
Classifier: Programming Language :: Python :: 3.9
Classifier: Programming Language :: Python :: 3.10
Classifier: Programming Language :: Python :: 3
Classifier: Programming Language :: Python :: 3.8
Classifier: Programming Language :: Python :: 3.9
Classifier: Topic :: Education
Requires-Dist: attrs (>=21.0.0,<23.0.0)
Requires-Dist: beautifulsoup4 (>=4.11.1,<5.0.0)
Requires-Dist: bleach (>=4.0.0,<6.0.0)
Requires-Dist: fuzzywuzzy (>=0.18.0,<0.19.0)
Requires-Dist: requests (>=2.28.1,<3.0.0)
Requires-Dist: requests-toolbelt (>=0.9.1,<0.10.0)
